reasonchip/__init__.py
reasonchip/chipsets/__init__.py
reasonchip/chipsets/http.py
reasonchip/chipsets/redis.py
reasonchip/chipsets/telegram.py
reasonchip/chipsets/reasonchip/__init__.py
reasonchip/chipsets/reasonchip/async.py
reasonchip/chipsets/reasonchip/debug.py
reasonchip/chipsets/reasonchip/streams.py
reasonchip/chipsets/reasoning/__init__.py
reasonchip/chipsets/reasoning/openai/__init__.py
reasonchip/chipsets/reasoning/openai/chat.py
reasonchip/chipsets/utils/__init__.py
reasonchip/chipsets/utils/json.py
reasonchip/chipsets/utils/strings.py
reasonchip/chipsets/utils/time.py
reasonchip/cli/__init__.py
reasonchip/cli/reasonchip.py
reasonchip/cli/commands/__init__.py
reasonchip/cli/commands/broker_command.py
reasonchip/cli/commands/command.py
reasonchip/cli/commands/exit_code.py
reasonchip/cli/commands/run_command.py
reasonchip/cli/commands/run_local_command.py
reasonchip/cli/commands/worker_command.py
reasonchip/core/__init__.py
reasonchip/core/exceptions.py
reasonchip/core/stack.py
reasonchip/core/config/__init__.py
reasonchip/core/config/config.py
reasonchip/core/config/loader.py
reasonchip/core/engine/__init__.py
reasonchip/core/engine/engine.py
reasonchip/core/engine/facilities.py
reasonchip/core/engine/flow_control.py
reasonchip/core/engine/parsers.py
reasonchip/core/engine/pipelines.py
reasonchip/core/engine/processor.py
reasonchip/core/engine/registry.py
reasonchip/core/engine/variables.py
reasonchip/core/logging/__init__.py
reasonchip/core/logging/configure.py
reasonchip/core/logging/system_formatter.py
reasonchip/data/README.md
reasonchip/data/logging.conf
reasonchip/net/__init__.py
reasonchip/net/protocol.py
reasonchip/net/broker/__init__.py
reasonchip/net/broker/broker.py
reasonchip/net/broker/switchboard.py
reasonchip/net/client/__init__.py
reasonchip/net/client/api.py
reasonchip/net/client/client.py
reasonchip/net/client/exceptions.py
reasonchip/net/client/multiplexor.py
reasonchip/net/transports/__init__.py
reasonchip-0.0.6.dist-info/licenses/LICENSE
reasonchip-0.0.6.dist-info/METADATA
reasonchip-0.0.6.dist-info/WHEEL
reasonchip-0.0.6.dist-info/entry_points.txt
reasonchip-0.0.6.dist-info/top_level.txt
reasonchip-0.0.6.dist-info/RECORD
