Metadata-Version: 2.4
Name: reasonchip
Version: 0.0.6
Summary: Reasoning workflow support
Author-email: South Patron LLC <support@reasonchip.io>
License-Expression: GPL-3.0-or-later
Project-URL: Homepage, https://www.reasonchip.io/
Project-URL: Source Code, https://github.com/SouthPatron/reasonchip
Project-URL: Bug Tracker, https://github.com/SouthPatron/reasonchip/issues/
Project-URL: Documentation, https://www.reasonchip.io/docs/
Classifier: Development Status :: 4 - Beta
Classifier: Environment :: Console
Classifier: Intended Audience :: Developers
Classifier: Intended Audience :: Information Technology
Classifier: Operating System :: POSIX
Classifier: Programming Language :: Python :: 3
Classifier: Topic :: Software Development :: Libraries
Classifier: Topic :: System :: Distributed Computing
Requires-Python: >=3.13
License-File: LICENSE
Requires-Dist: setproctitle>=1.3.4
Requires-Dist: black>=25.1.0
Requires-Dist: pre-commit>=4.2.0
Requires-Dist: ruamel.yaml>=0.18.6
Requires-Dist: munch>=4.0.0
Requires-Dist: pydantic>=2
Requires-Dist: fastapi>=0.115.6
Requires-Dist: hypercorn[h3]>=0.17.3
Requires-Dist: grpcio>=1.68.1
Requires-Dist: grpcio-reflection>=1.68.1
Requires-Dist: grpcio-tools>=1.68.1
Requires-Dist: SQLAlchemy>=2.0.40
Requires-Dist: asyncpg>=0.30.0
Requires-Dist: aiosqlite>=0.21.0
Requires-Dist: diff-match-patch>=20241021
Requires-Dist: httpx>=0.28.1
Requires-Dist: openai>=1.61.1
Requires-Dist: redis[hiredis]>=5.2.1
Requires-Dist: python-telegram-bot>=21.10
Dynamic: license-file
